README.md
setup.py
ligature/__init__.py
ligature/_compat.py
ligature/calculation.py
ligature/compose.py
ligature/easing.py
ligature/enum.py
ligature/examples.py
ligature/expression.py
ligature/graph.py
ligature/record.py
ligature/recordset.py
ligature/scanner.py
ligature/transform.py
ligature/update.py
ligature.egg-info/PKG-INFO
ligature.egg-info/SOURCES.txt
ligature.egg-info/dependency_links.txt
ligature.egg-info/top_level.txt
ligature/calculations/__init__.py
ligature/calculations/aggregate.py
ligature/calculations/cluster.py
ligature/calculations/sweep.py
ligature/calculations/window.py
ligature/scanners/__init__.py
ligature/scanners/chunk.py
ligature/scanners/element.py
ligature/scanners/group.py
ligature/scanners/identity.py
ligature/scanners/record.py
ligature/scanners/replaying.py
ligature/simulators/__init__.py
ligature/simulators/drunk.py
ligature/simulators/process.py
ligature/simulators/mixins/__init__.py
ligature/simulators/mixins/easing.py
ligature/simulators/mixins/expression.py
ligature/simulators/mixins/graph.py
ligature/simulators/mixins/support.py
ligature/simulators/mixins/tags.py
ligature/tests/__init__.py
ligature/tests/test_expression.py
ligature/tests/test_record.py
ligature/tests/calculations/__init__.py
ligature/tests/calculations/test_aggregate.py
ligature/tests/calculations/test_cluster.py
ligature/tests/calculations/test_sweep.py
ligature/tests/calculations/test_window.py
ligature/tests/scanners/__init__.py
ligature/tests/scanners/test_chunk.py
ligature/tests/scanners/test_element.py
ligature/tests/scanners/test_group.py
ligature/tests/scanners/test_record.py
ligature/tests/scanners/test_replaying.py
ligature/tests/transforms/__init__.py
ligature/tests/transforms/test_merge.py
ligature/tests/transforms/test_pivot.py
ligature/tests/transforms/test_regroup.py
ligature/transforms/__init__.py
ligature/transforms/cluster.py
ligature/transforms/collation.py
ligature/transforms/feed.py
ligature/transforms/lagBucket.py
ligature/transforms/merge.py
ligature/transforms/pivot.py
ligature/transforms/regroup.py
ligature/transforms/unvacuum.py