Metadata-Version: 2.1
Name: ligature
Version: 1.5.0
Summary: A ~toy~ useful Python library for merging data, from low to high level abstractions.
Home-page: https://github.com/CorsoSource/ligature
Author: Andrew Geiger
Author-email: andrew.geiger@corsosystems.com
License: UNKNOWN
Platform: UNKNOWN
Classifier: Development Status :: 4 - Beta
Classifier: Programming Language :: Python :: 2
Classifier: License :: OSI Approved :: Apache Software License
Classifier: Operating System :: OS Independent
Requires-Python: >=2.5
